docgenie/cli/__init__.py
docgenie/main.py
docgenie/model.py
docgenie/models/__init__.py
docgenie/models/custom_api.py
docgenie/models/gemini.py
docgenie/prompts.py
docgenie/utils/file.py
docgenie/utils/languages.py
docgenie/utils/patterns.py
docgenie/utils/terminal.py
docgenie-0.0.3.dist-info/entry_points.txt
docgenie-0.0.3.dist-info/LICENSE
docgenie-0.0.3.dist-info/METADATA
docgenie-0.0.3.dist-info/WHEEL
docgenie-0.0.3.dist-info/RECORD
