Metadata-Version: 2.1
Name: docgenie
Version: 0.0.3
Summary: A tool for generating documentation
License: MIT
Author: Ujjwal Jindal
Author-email: jindalujjwal0720@gmail.com
Requires-Python: >=3.8.1,<4.0.0
Classifier: License :: OSI Approved :: MIT License
Classifier: Programming Language :: Python :: 3
Classifier: Programming Language :: Python :: 3.9
Classifier: Programming Language :: Python :: 3.10
Classifier: Programming Language :: Python :: 3.11
Classifier: Programming Language :: Python :: 3.12
Requires-Dist: click (>=8.1.7,<9.0.0)
Requires-Dist: inquirer (>=3.4.0,<4.0.0)
Requires-Dist: python-dotenv (>=1.0.1,<2.0.0)
